[
  {
    "ContainingType": "webApiSimulation.Controllers.MachinesController",
    "Method": "GetAll",
    "RelativePath": "api/Machines",
    "HttpMethod": "GET",
    "IsController": true,
    "Order": 0,
    "Parameters": [],
    "ReturnTypes": [
      {
        "Type": "System.Collections.Generic.List\u00601[[webApiSimulation.Models.Machine, webApiSimulation, Version=1.0.0.0, Culture=neutral, PublicKeyToken=null]]",
        "MediaTypes": [
          "text/plain",
          "application/json",
          "text/json"
        ],
        "StatusCode": 200
      }
    ]
  },
  {
    "ContainingType": "webApiSimulation.Controllers.MachinesController",
    "Method": "Add",
    "RelativePath": "api/Machines",
    "HttpMethod": "POST",
    "IsController": true,
    "Order": 0,
    "Parameters": [
      {
        "Name": "machines",
        "Type": "System.Collections.Generic.List\u00601[[webApiSimulation.Models.Machine, webApiSimulation, Version=1.0.0.0, Culture=neutral, PublicKeyToken=null]]",
        "IsRequired": true
      }
    ],
    "ReturnTypes": []
  },
  {
    "ContainingType": "webApiSimulation.Controllers.MachinesController",
    "Method": "GetByAbbreviation",
    "RelativePath": "api/Machines/{abbreviation}",
    "HttpMethod": "GET",
    "IsController": true,
    "Order": 0,
    "Parameters": [
      {
        "Name": "abbreviation",
        "Type": "System.String",
        "IsRequired": true
      }
    ],
    "ReturnTypes": [
      {
        "Type": "webApiSimulation.Models.Machine",
        "MediaTypes": [
          "text/plain",
          "application/json",
          "text/json"
        ],
        "StatusCode": 200
      }
    ]
  }
]